pyafkalib/__init__.py
pyafkalib/deserializers.py
pyafkalib/pyafka.py
pyafka-0.2.0.dist-info/LICENSE
pyafka-0.2.0.dist-info/METADATA
pyafka-0.2.0.dist-info/WHEEL
pyafka-0.2.0.dist-info/top_level.txt
pyafka-0.2.0.dist-info/RECORD
