Metadata-Version: 2.1
Name: pyafka
Version: 0.2.0
Summary: Kafka framework
Home-page: UNKNOWN
Author: Jacek Kufel
License: Apache License 2.0 
Platform: UNKNOWN
Requires-Dist: confluent-kafka (==1.5.0)
